streamlit_firebase_auth/__init__.py
streamlit_firebase_auth/frontend/.env
streamlit_firebase_auth/frontend/.prettierrc
streamlit_firebase_auth/frontend/package-lock.json
streamlit_firebase_auth/frontend/package.json
streamlit_firebase_auth/frontend/tsconfig.json
streamlit_firebase_auth/frontend/build/asset-manifest.json
streamlit_firebase_auth/frontend/build/bootstrap.min.css
streamlit_firebase_auth/frontend/build/bootstrap.min.css.map
streamlit_firebase_auth/frontend/build/index.html
streamlit_firebase_auth/frontend/build/static/js/main.274d6bab.js
streamlit_firebase_auth/frontend/build/static/js/main.274d6bab.js.LICENSE.txt
streamlit_firebase_auth/frontend/build/static/js/main.274d6bab.js.map
streamlit_firebase_auth/frontend/config/env.js
streamlit_firebase_auth/frontend/config/getHttpsConfig.js
streamlit_firebase_auth/frontend/config/modules.js
streamlit_firebase_auth/frontend/config/paths.js
streamlit_firebase_auth/frontend/config/webpack.config.js
streamlit_firebase_auth/frontend/config/webpackDevServer.config.js
streamlit_firebase_auth/frontend/config/jest/babelTransform.js
streamlit_firebase_auth/frontend/config/jest/cssTransform.js
streamlit_firebase_auth/frontend/config/jest/fileTransform.js
streamlit_firebase_auth/frontend/config/webpack/persistentCache/createEnvironmentHash.js
streamlit_firebase_auth/frontend/public/bootstrap.min.css
streamlit_firebase_auth/frontend/public/bootstrap.min.css.map
streamlit_firebase_auth/frontend/public/index.html
streamlit_firebase_auth/frontend/scripts/build.js
streamlit_firebase_auth/frontend/scripts/start.js
streamlit_firebase_auth/frontend/scripts/test.js
streamlit_firebase_auth/frontend/src/Auth.tsx
streamlit_firebase_auth/frontend/src/index.tsx
streamlit_firebase_auth/frontend/src/react-app-env.d.ts
streamlit_firebase_auth-1.1.6.dist-info/METADATA
streamlit_firebase_auth-1.1.6.dist-info/WHEEL
streamlit_firebase_auth-1.1.6.dist-info/licenses/LICENSE
streamlit_firebase_auth-1.1.6.dist-info/RECORD
