Metadata-Version: 2.4
Name: streamlit-firebase-auth
Version: 1.1.6
Summary: Streamlit component for Firebae auth
Project-URL: Homepage, https://github.com/munaita-0/streamlit-firebase-auth
Author-email: Suzuki Shogo <suzuki.shogo@commondo.jp>
License-File: LICENSE
Classifier: License :: OSI Approved :: MIT License
Classifier: Operating System :: OS Independent
Classifier: Programming Language :: Python :: 3
Requires-Python: >=3.11
Requires-Dist: build>=1.2.2.post1
Requires-Dist: firebase-admin
Requires-Dist: twine>=6.1.0
